{
  "items": [
    {
      "title": "Tor-Based Clipper Malware Targets Wallet Seed Phrases",
      "url": "https://securityaffairs.com/193860/uncategorized/tor-based-clipper-malware-targets-wallet-seed-phrases.html",
      "published": "Thu, 18 Jun 2026 18:32:32 +0000",
      "source": "Security Affairs"
    },
    {
      "title": "Operation Endgame Disrupts SocGholish Servers, Cleans 14,971 WordPress Sites",
      "url": "https://thehackernews.com/2026/06/operation-endgame-disrupts-socgholish.html",
      "published": "Fri, 19 Jun 2026 20:37:54 +0530",
      "source": "The Hacker News"
    },
    {
      "title": "CISA Warns Fortinet Customers as FortiBleed Hits 86,644 FortiGate Devices",
      "url": "https://thehackernews.com/2026/06/cisa-warns-fortinet-customers-as.html",
      "published": "Fri, 19 Jun 2026 19:30:21 +0530",
      "source": "The Hacker News"
    }
  ]
}